{
  "lastUpdated": "2026-05-18T17:36:06.432Z",
  "marketOpen": true,
  "instruments": {
    "SPY": {
      "ticker": "SPY",
      "currentPrice": 736.85,
      "change": -2.3199999999999363,
      "changePercent": -0.3138655519028013,
      "previousClose": 739.17,
      "high": 741.415,
      "low": 734.225,
      "open": 737.7650000000001,
      "sparkline": [
        736.29,
        735.865,
        736.24,
        736.94,
        737.22,
        736.76,
        734.81,
        735.465,
        735.7,
        735.16,
        735.47,
        736.84,
        736.5,
        736.89,
        736.965,
        736.74,
        737.24,
        736.9,
        737.38,
        736.86
      ]
    },
    "QQQ": {
      "ticker": "QQQ",
      "currentPrice": 703.01,
      "change": -5.919999999999959,
      "changePercent": -0.835061289549033,
      "previousClose": 708.93,
      "high": 712.07,
      "low": 699.61,
      "open": 708.915,
      "sparkline": [
        703.205,
        702.64,
        703.21,
        703.96,
        704.14,
        703.22,
        700.41,
        701.29,
        701.79,
        701.49,
        701.64,
        703.81,
        703.48,
        703.58,
        703.665,
        703.3,
        703.39,
        702.8,
        703.62,
        703.03
      ]
    },
    "IWM": {
      "ticker": "IWM",
      "currentPrice": 275.55,
      "change": -2.0500000000000114,
      "changePercent": -0.7384726224783902,
      "previousClose": 277.6,
      "high": 279.08,
      "low": 274.92,
      "open": 277.62,
      "sparkline": [
        275.885,
        275.71,
        275.75,
        276.32,
        276.43,
        276.06,
        275.16,
        275.57,
        275.54,
        275.26,
        275.39,
        276,
        275.81,
        275.92,
        275.96,
        275.87,
        276.06,
        275.83,
        275.85,
        275.55
      ]
    },
    "VIXY": {
      "ticker": "VIXY",
      "currentPrice": 26.47,
      "change": -0.46000000000000085,
      "changePercent": -1.7081321945785402,
      "previousClose": 26.93,
      "high": 26.83,
      "low": 26.295,
      "open": 26.560000000000002,
      "sparkline": [
        26.54,
        26.58,
        26.52,
        26.46,
        26.37,
        26.44,
        26.63,
        26.55,
        26.52,
        26.58,
        26.54,
        26.405,
        26.4,
        26.42,
        26.4,
        26.4,
        26.39,
        26.41,
        26.46,
        26.465
      ]
    },
    "IEF": {
      "ticker": "IEF",
      "currentPrice": 93.53,
      "change": 0.01999999999999602,
      "changePercent": 0.021388086835628296,
      "previousClose": 93.51,
      "high": 93.7482,
      "low": 93.45,
      "open": 93.59,
      "sparkline": [
        93.52,
        93.53,
        93.54,
        93.535,
        93.53,
        93.57,
        93.52,
        93.48,
        93.54,
        93.55,
        93.55,
        93.555,
        93.53,
        93.545,
        93.51,
        93.555,
        93.57,
        93.55,
        93.515,
        93.515
      ]
    },
    "URTH": {
      "ticker": "URTH",
      "currentPrice": 199.74,
      "change": -0.1799999999999784,
      "changePercent": -0.0900360144057515,
      "previousClose": 199.92,
      "high": 200.86,
      "low": 199.11,
      "open": 200.65
    },
    "ACWI": {
      "ticker": "ACWI",
      "currentPrice": 154.02,
      "change": -0.060000000000002274,
      "changePercent": -0.03894080996884883,
      "previousClose": 154.08,
      "high": 154.97,
      "low": 153.5,
      "open": 154.88
    },
    "RSP": {
      "ticker": "RSP",
      "currentPrice": 202.42,
      "change": 0.8599999999999852,
      "changePercent": 0.4266719587219613,
      "previousClose": 201.56,
      "high": 203.28,
      "low": 201.38,
      "open": 201.38
    },
    "VTV": {
      "ticker": "VTV",
      "currentPrice": 206.91,
      "change": 0.2400000000000091,
      "changePercent": 0.11612715923937152,
      "previousClose": 206.67,
      "high": 207.66,
      "low": 206.54,
      "open": 206.69
    },
    "VUG": {
      "ticker": "VUG",
      "currentPrice": 86.9,
      "change": -0.5300000000000011,
      "changePercent": -0.6061992451103753,
      "previousClose": 87.43,
      "high": 87.66,
      "low": 86.4147,
      "open": 87.2575
    },
    "XLK": {
      "ticker": "XLK",
      "currentPrice": 173.27,
      "change": -2.9899999999999807,
      "changePercent": -1.696357653466459,
      "previousClose": 176.26,
      "high": 177.85,
      "low": 172.14,
      "open": 176.615
    },
    "XLF": {
      "ticker": "XLF",
      "currentPrice": 51.66,
      "change": 0.5599999999999952,
      "changePercent": 1.0958904109588945,
      "previousClose": 51.1,
      "high": 51.765,
      "low": 50.95,
      "open": 50.95
    },
    "XLE": {
      "ticker": "XLE",
      "currentPrice": 60.41,
      "change": 0.9699999999999989,
      "changePercent": 1.631897711978464,
      "previousClose": 59.44,
      "high": 60.67,
      "low": 58.72,
      "open": 59.4375
    },
    "XLV": {
      "ticker": "XLV",
      "currentPrice": 145.55,
      "change": 0.45000000000001705,
      "changePercent": 0.3101309441764418,
      "previousClose": 145.1,
      "high": 145.75,
      "low": 144.12,
      "open": 144.505
    },
    "XLY": {
      "ticker": "XLY",
      "currentPrice": 116.32,
      "change": -0.21000000000000796,
      "changePercent": -0.18021110443663257,
      "previousClose": 116.53,
      "high": 117.78,
      "low": 116.15,
      "open": 116.175
    },
    "XLP": {
      "ticker": "XLP",
      "currentPrice": 85.48,
      "change": 0.8400000000000034,
      "changePercent": 0.9924385633270363,
      "previousClose": 84.64,
      "high": 85.78,
      "low": 84.68,
      "open": 84.685
    },
    "AAPL": {
      "ticker": "AAPL",
      "currentPrice": 296.12,
      "change": -4.110000000000014,
      "changePercent": -1.3689504713053369,
      "previousClose": 300.23,
      "high": 300.66,
      "low": 294.91,
      "open": 299.795
    },
    "MSFT": {
      "ticker": "MSFT",
      "currentPrice": 422.94,
      "change": 1.0199999999999818,
      "changePercent": 0.24175199089874425,
      "previousClose": 421.92,
      "high": 424.16,
      "low": 415.61,
      "open": 418.435
    },
    "NVDA": {
      "ticker": "NVDA",
      "currentPrice": 221.35,
      "change": -3.969999999999999,
      "changePercent": -1.7619385762471147,
      "previousClose": 225.32,
      "high": 230,
      "low": 219.6402,
      "open": 227.24
    },
    "AMZN": {
      "ticker": "AMZN",
      "currentPrice": 265.05,
      "change": 0.910000000000025,
      "changePercent": 0.3445142727341656,
      "previousClose": 264.14,
      "high": 268.85,
      "low": 262.53,
      "open": 263.1825
    },
    "JPM": {
      "ticker": "JPM",
      "currentPrice": 300.69,
      "change": 2.8799999999999955,
      "changePercent": 0.9670595346025974,
      "previousClose": 297.81,
      "high": 301.26,
      "low": 297.22,
      "open": 297.57
    }
  },
  "compassData": {
    "direction": {
      "spy": {
        "price": 736.602,
        "ma200": 676.59,
        "percentVs200MA": 8.87,
        "dailyChange": -0.35
      },
      "qqq": {
        "price": 702.88,
        "ma200": 611.64,
        "percentVs200MA": 14.92,
        "dailyChange": -0.85
      },
      "iwm": {
        "price": 275.41,
        "ma200": 251.33,
        "percentVs200MA": 9.58,
        "dailyChange": -0.79
      }
    },
    "volatility": {
      "vix": {
        "value": 18.31,
        "dailyChange": -0.12,
        "isContango": true
      },
      "putCall": {
        "ratio": 0.85,
        "change": 0
      }
    },
    "breadth": {
      "advancers": 1800,
      "decliners": 1200,
      "percentAbove200MA": 60,
      "percentAbove200MAChange": 0,
      "newHighs": 75,
      "newLows": 30
    },
    "credit": {
      "treasury10Y": 4.15,
      "treasury2Y": 3.95,
      "yieldCurveSpread": 0.2,
      "yieldCurveChange": 0,
      "hySpread": 3.5,
      "hySpreadChange": 0,
      "igSpread": 1.2,
      "igSpreadChange": 0
    },
    "sentiment": {
      "fearGreed": 50,
      "fearGreedChange": 0,
      "bulls": 35.2,
      "bears": 29.8,
      "bullsChange": 1.2,
      "bearsChange": -0.8
    },
    "global": {
      "acwi": {
        "price": 153.95,
        "percentVs50MA": 5.37,
        "dailyChange": -0.09
      },
      "vstoxx": {
        "value": 17,
        "change": 0
      },
      "pmi": {
        "value": 52.3,
        "change": 0.4
      }
    }
  }
}