{
  "lastUpdated": "2026-05-21T19:38:55.546Z",
  "marketOpen": true,
  "instruments": {
    "SPY": {
      "ticker": "SPY",
      "currentPrice": 742.72,
      "change": 1.4700000000000273,
      "changePercent": 0.19831365935919423,
      "previousClose": 741.25,
      "high": 744.87,
      "low": 737.03,
      "open": 739.525
    },
    "QQQ": {
      "ticker": "QQQ",
      "currentPrice": 714.01,
      "change": 0.8600000000000136,
      "changePercent": 0.120591740867982,
      "previousClose": 713.15,
      "high": 717.12,
      "low": 706.77,
      "open": 710.38
    },
    "IWM": {
      "ticker": "IWM",
      "currentPrice": 282.51,
      "change": 2.6399999999999864,
      "changePercent": 0.9432951012970259,
      "previousClose": 279.87,
      "high": 283.68,
      "low": 277.15,
      "open": 279.07000000000005,
      "sparkline": [
        282.52,
        282.87,
        282.76,
        283.03,
        283.38,
        283.39,
        283.26,
        283.23,
        283.41,
        282.66,
        281.59,
        281.91,
        282.39,
        282.54,
        282.73,
        282.735,
        282.53,
        282.46,
        282.28,
        282.475
      ]
    },
    "VIXY": {
      "ticker": "VIXY",
      "currentPrice": 25.2,
      "change": -0.8200000000000003,
      "changePercent": -3.1514219830899317,
      "previousClose": 26.02,
      "high": 26.36,
      "low": 25.185,
      "open": 26.290000000000003,
      "sparkline": [
        25.47,
        25.425,
        25.405,
        25.39,
        25.38,
        25.4,
        25.36,
        25.38,
        25.42,
        25.46,
        25.605,
        25.5,
        25.43,
        25.36,
        25.4,
        25.35,
        25.34,
        25.355,
        25.21,
        25.21
      ]
    },
    "IEF": {
      "ticker": "IEF",
      "currentPrice": 93.79,
      "change": 0.05000000000001137,
      "changePercent": 0.0533390228291139,
      "previousClose": 93.74,
      "high": 93.835,
      "low": 93.305,
      "open": 93.595,
      "sparkline": [
        93.81,
        93.76,
        93.77,
        93.79,
        93.81,
        93.81,
        93.77,
        93.775,
        93.8,
        93.74,
        93.67,
        93.63,
        93.685,
        93.67,
        93.69,
        93.7,
        93.73,
        93.71,
        93.725,
        93.76
      ]
    },
    "URTH": {
      "ticker": "URTH",
      "currentPrice": 201.98,
      "change": 0.4899999999999807,
      "changePercent": 0.24318824755570037,
      "previousClose": 201.49,
      "high": 202.52,
      "low": 199.88,
      "open": 200.115
    },
    "ACWI": {
      "ticker": "ACWI",
      "currentPrice": 155.76,
      "change": 0.6599999999999966,
      "changePercent": 0.42553191489361486,
      "previousClose": 155.1,
      "high": 156.195,
      "low": 154.25,
      "open": 154.525
    },
    "RSP": {
      "ticker": "RSP",
      "currentPrice": 204.68,
      "change": 0.8499999999999943,
      "changePercent": 0.4170141784820656,
      "previousClose": 203.83,
      "high": 204.9,
      "low": 201.81,
      "open": 203.485
    },
    "VTV": {
      "ticker": "VTV",
      "currentPrice": 208.9,
      "change": 0.5200000000000102,
      "changePercent": 0.24954410212112976,
      "previousClose": 208.38,
      "high": 209.04,
      "low": 206.55,
      "open": 208.01
    },
    "VUG": {
      "ticker": "VUG",
      "currentPrice": 87.53,
      "change": 0.12999999999999545,
      "changePercent": 0.14874141876429686,
      "previousClose": 87.4,
      "high": 87.925,
      "low": 86.745,
      "open": 87.095
    },
    "XLK": {
      "ticker": "XLK",
      "currentPrice": 178.18,
      "change": 1.0400000000000205,
      "changePercent": 0.5871062436491027,
      "previousClose": 177.14,
      "high": 178.98,
      "low": 175.83,
      "open": 176.385
    },
    "XLF": {
      "ticker": "XLF",
      "currentPrice": 51.73,
      "change": 0.07000000000000028,
      "changePercent": 0.1355013550135507,
      "previousClose": 51.66,
      "high": 51.83,
      "low": 51.21,
      "open": 51.6
    },
    "XLE": {
      "ticker": "XLE",
      "currentPrice": 59.33,
      "change": -0.46999999999999886,
      "changePercent": -0.7859531772575232,
      "previousClose": 59.8,
      "high": 60.59,
      "low": 58.715,
      "open": 60.17
    },
    "XLV": {
      "ticker": "XLV",
      "currentPrice": 148.21,
      "change": 1.0800000000000125,
      "changePercent": 0.734044722354389,
      "previousClose": 147.13,
      "high": 148.27,
      "low": 145.84,
      "open": 147.085
    },
    "XLY": {
      "ticker": "XLY",
      "currentPrice": 118.87,
      "change": 0.9300000000000068,
      "changePercent": 0.7885365440054323,
      "previousClose": 117.94,
      "high": 119.215,
      "low": 116.805,
      "open": 118.07
    },
    "XLP": {
      "ticker": "XLP",
      "currentPrice": 84.76,
      "change": -0.7599999999999909,
      "changePercent": -0.88868101028998,
      "previousClose": 85.52,
      "high": 85.025,
      "low": 83.44,
      "open": 85.025
    },
    "AAPL": {
      "ticker": "AAPL",
      "currentPrice": 305.13,
      "change": 2.8799999999999955,
      "changePercent": 0.9528535980148868,
      "previousClose": 302.25,
      "high": 305.54,
      "low": 300.4,
      "open": 301.0775
    },
    "MSFT": {
      "ticker": "MSFT",
      "currentPrice": 418.86,
      "change": -2.1999999999999886,
      "changePercent": -0.5224908564100101,
      "previousClose": 421.06,
      "high": 426.34,
      "low": 415.71,
      "open": 421.64
    },
    "NVDA": {
      "ticker": "NVDA",
      "currentPrice": 220.41,
      "change": -3.0600000000000023,
      "changePercent": -1.369311316955297,
      "previousClose": 223.47,
      "high": 227.3999,
      "low": 217.93,
      "open": 222.32999999999998
    },
    "AMZN": {
      "ticker": "AMZN",
      "currentPrice": 268.6,
      "change": 3.590000000000032,
      "changePercent": 1.3546658616656095,
      "previousClose": 265.01,
      "high": 269.4899,
      "low": 261.37,
      "open": 264.255
    },
    "JPM": {
      "ticker": "JPM",
      "currentPrice": 302.84,
      "change": 0.8599999999999568,
      "changePercent": 0.2847870719915083,
      "previousClose": 301.98,
      "high": 303.975,
      "low": 300.21,
      "open": 302.08500000000004
    }
  },
  "compassData": {
    "direction": {
      "spy": {
        "price": 742.71,
        "ma200": 678.29,
        "percentVs200MA": 9.5,
        "dailyChange": 0.2
      },
      "qqq": {
        "price": 714.02,
        "ma200": 613.91,
        "percentVs200MA": 16.31,
        "dailyChange": 0.12
      },
      "iwm": {
        "price": 282.56,
        "ma200": 252.23,
        "percentVs200MA": 12.02,
        "dailyChange": 0.96
      }
    },
    "volatility": {
      "vix": {
        "value": 16.86,
        "dailyChange": -0.58,
        "isContango": true
      },
      "putCall": {
        "ratio": 0.85,
        "change": 0
      }
    },
    "breadth": {
      "advancers": 1800,
      "decliners": 1200,
      "percentAbove200MA": 90,
      "percentAbove200MAChange": 0,
      "newHighs": 75,
      "newLows": 30
    },
    "credit": {
      "treasury10Y": 4.15,
      "treasury2Y": 3.95,
      "yieldCurveSpread": 0.2,
      "yieldCurveChange": 0,
      "hySpread": 3.5,
      "hySpreadChange": 0,
      "igSpread": 1.2,
      "igSpreadChange": 0
    },
    "sentiment": {
      "fearGreed": 50,
      "fearGreedChange": 0,
      "bulls": 35.2,
      "bears": 29.8,
      "bullsChange": 1.2,
      "bearsChange": -0.8
    },
    "global": {
      "acwi": {
        "price": 155.73,
        "percentVs50MA": 6.08,
        "dailyChange": 0.41
      },
      "vstoxx": {
        "value": 17,
        "change": 0
      },
      "pmi": {
        "value": 52.3,
        "change": 0.4
      }
    }
  }
}