{
  "lastUpdated": "2026-02-18T17:09:32.301Z",
  "marketOpen": true,
  "instruments": {
    "SPY": {
      "ticker": "SPY",
      "currentPrice": 688.54,
      "change": 5.689999999999941,
      "changePercent": 0.8332723145639511,
      "previousClose": 682.85,
      "high": 688.96,
      "low": 682.83,
      "open": 686.04,
      "sparkline": [
        687.33,
        688.08,
        688.25,
        688.34,
        688.46,
        688.515,
        688.56,
        688.36,
        688.42,
        688.2,
        688.33,
        688.22,
        688.45,
        688.54,
        688.33,
        688.06,
        687.75,
        687.55,
        688.155,
        688.53
      ]
    },
    "QQQ": {
      "ticker": "QQQ",
      "currentPrice": 609.36,
      "change": 8.06000000000006,
      "changePercent": 1.3404290703475903,
      "previousClose": 601.3,
      "high": 609.771,
      "low": 600.72,
      "open": 604.33,
      "sparkline": [
        607.225,
        608.01,
        608.26,
        608.4,
        608.7,
        608.775,
        609.09,
        608.78,
        609.02,
        608.75,
        608.99,
        608.94,
        609.14,
        609.32,
        609.2,
        608.84,
        608.39,
        608.18,
        608.97,
        609.33
      ]
    },
    "IWM": {
      "ticker": "IWM",
      "currentPrice": 265.72,
      "change": 2.680000000000007,
      "changePercent": 1.018856447688567,
      "previousClose": 263.04,
      "high": 266.91,
      "low": 261.85,
      "open": 263.8,
      "sparkline": [
        266.54,
        266.83,
        266.61,
        266.415,
        266.35,
        266.4,
        266.18,
        266.11,
        265.905,
        265.71,
        265.74,
        265.93,
        265.84,
        265.97,
        265.77,
        265.55,
        265.61,
        265.43,
        265.68,
        265.73
      ]
    },
    "VIXY": {
      "ticker": "VIXY",
      "currentPrice": 26.98,
      "change": -0.3200000000000003,
      "changePercent": -1.172161172161173,
      "previousClose": 27.3,
      "high": 27.6,
      "low": 26.72,
      "open": 27.42,
      "sparkline": [
        26.96,
        26.97,
        26.89,
        26.91,
        26.89,
        26.87,
        26.82,
        26.81,
        26.79,
        26.88,
        26.925,
        26.95,
        26.96,
        26.92,
        26.885,
        26.92,
        26.98,
        27.05,
        27.09,
        27.005
      ]
    },
    "IEF": {
      "ticker": "IEF",
      "currentPrice": 97.09,
      "change": -0.10999999999999943,
      "changePercent": -0.11316872427983479,
      "previousClose": 97.2,
      "high": 97.1,
      "low": 96.995,
      "open": 97.1,
      "sparkline": [
        97.01,
        97.02,
        97.02,
        97.02,
        97.03,
        97.04,
        97.05,
        97.06,
        97.05,
        97.04,
        97.05,
        97.06,
        97.05,
        97.05,
        97.055,
        97.06,
        97.06,
        97.065,
        97.075,
        97.075
      ]
    },
    "URTH": {
      "ticker": "URTH",
      "currentPrice": 191.04,
      "change": 1.579999999999984,
      "changePercent": 0.8339491185474421,
      "previousClose": 189.46,
      "high": 191.05,
      "low": 189.49,
      "open": 189.65
    },
    "ACWI": {
      "ticker": "ACWI",
      "currentPrice": 147.18,
      "change": 1.1800000000000068,
      "changePercent": 0.8082191780821966,
      "previousClose": 146,
      "high": 147.29,
      "low": 146.05,
      "open": 146.27
    },
    "RSP": {
      "ticker": "RSP",
      "currentPrice": 204,
      "change": 1.4799999999999898,
      "changePercent": 0.7307920205411761,
      "previousClose": 202.52,
      "high": 204.2,
      "low": 202.25,
      "open": 203.36
    },
    "VTV": {
      "ticker": "VTV",
      "currentPrice": 206.84,
      "change": 0.9900000000000091,
      "changePercent": 0.48093271799854703,
      "previousClose": 205.85,
      "high": 207.11,
      "low": 205.68,
      "open": 206.33
    },
    "VUG": {
      "ticker": "VUG",
      "currentPrice": 464.81,
      "change": 5.28000000000003,
      "changePercent": 1.149000065284101,
      "previousClose": 459.53,
      "high": 465.2427,
      "low": 459.37,
      "open": 461.9
    },
    "XLK": {
      "ticker": "XLK",
      "currentPrice": 142,
      "change": 2.5200000000000102,
      "changePercent": 1.8067106395182178,
      "previousClose": 139.48,
      "high": 142.115,
      "low": 139.27,
      "open": 140.32
    },
    "XLF": {
      "ticker": "XLF",
      "currentPrice": 52.65,
      "change": 0.44999999999999574,
      "changePercent": 0.8620689655172332,
      "previousClose": 52.2,
      "high": 52.78,
      "low": 52.275,
      "open": 52.49
    },
    "XLE": {
      "ticker": "XLE",
      "currentPrice": 54.57,
      "change": 0.8200000000000003,
      "changePercent": 1.5255813953488377,
      "previousClose": 53.75,
      "high": 54.68,
      "low": 54.03,
      "open": 54.03
    },
    "XLV": {
      "ticker": "XLV",
      "currentPrice": 157.13,
      "change": -0.2400000000000091,
      "changePercent": -0.15250683103514587,
      "previousClose": 157.37,
      "high": 157.45,
      "low": 156.48,
      "open": 157.37
    },
    "XLY": {
      "ticker": "XLY",
      "currentPrice": 117.69,
      "change": 1.6499999999999915,
      "changePercent": 1.4219234746639016,
      "previousClose": 116.04,
      "high": 117.755,
      "low": 115.935,
      "open": 116.68
    },
    "XLP": {
      "ticker": "XLP",
      "currentPrice": 88.29,
      "change": 0.09000000000000341,
      "changePercent": 0.10204081632653449,
      "previousClose": 88.2,
      "high": 88.52,
      "low": 87.62,
      "open": 88.34
    },
    "AAPL": {
      "ticker": "AAPL",
      "currentPrice": 265.76,
      "change": 1.8799999999999955,
      "changePercent": 0.7124450507806561,
      "previousClose": 263.88,
      "high": 266.82,
      "low": 262.45,
      "open": 265.1
    },
    "MSFT": {
      "ticker": "MSFT",
      "currentPrice": 401.79,
      "change": 4.930000000000007,
      "changePercent": 1.2422516756538846,
      "previousClose": 396.86,
      "high": 402.56,
      "low": 396.32,
      "open": 399.28
    },
    "NVDA": {
      "ticker": "NVDA",
      "currentPrice": 189.44,
      "change": 4.469999999999999,
      "changePercent": 2.416608098610585,
      "previousClose": 184.97,
      "high": 190.37,
      "low": 187.35,
      "open": 187.7
    },
    "AMZN": {
      "ticker": "AMZN",
      "currentPrice": 206.06,
      "change": 4.909999999999997,
      "changePercent": 2.4409644543872715,
      "previousClose": 201.15,
      "high": 206.86,
      "low": 201.51,
      "open": 202.66
    },
    "JPM": {
      "ticker": "JPM",
      "currentPrice": 310.53,
      "change": 3.3999999999999773,
      "changePercent": 1.1070230846872586,
      "previousClose": 307.13,
      "high": 312.28,
      "low": 307.22,
      "open": 308.53
    }
  }
}