{
  "lastUpdated": "2026-03-27T15:48:06.757Z",
  "marketOpen": true,
  "instruments": {
    "SPY": {
      "ticker": "SPY",
      "currentPrice": 640.86,
      "change": -4.230000000000018,
      "changePercent": -0.6557224573315379,
      "previousClose": 645.09,
      "high": 645.05,
      "low": 638.3,
      "open": 645.05,
      "sparkline": [
        639.82,
        640.5,
        639.77,
        639.17,
        639.71,
        638.85,
        639.03,
        640.22,
        639.54,
        640.17,
        640.755,
        640.15,
        639.76,
        639.36,
        640.17,
        640.96,
        641.81,
        641.15,
        640.68,
        640.82
      ]
    },
    "QQQ": {
      "ticker": "QQQ",
      "currentPrice": 568.39,
      "change": -5.399999999999977,
      "changePercent": -0.9411108593736346,
      "previousClose": 573.79,
      "high": 573.365,
      "low": 565.66,
      "open": 573.365,
      "sparkline": [
        567.635,
        568.05,
        567.22,
        566.56,
        566.99,
        566.05,
        566.25,
        567.585,
        566.8,
        567.38,
        567.89,
        567.39,
        566.96,
        566.53,
        567.54,
        568.31,
        569.41,
        568.64,
        568.11,
        568.34
      ]
    },
    "IWM": {
      "ticker": "IWM",
      "currentPrice": 246.01,
      "change": -1.4300000000000068,
      "changePercent": -0.5779178790818004,
      "previousClose": 247.44,
      "high": 247.285,
      "low": 244.135,
      "open": 247.285,
      "sparkline": [
        245.045,
        245.53,
        245.05,
        244.785,
        245.17,
        244.53,
        244.51,
        245.26,
        244.995,
        245.44,
        245.76,
        245.31,
        245.13,
        244.73,
        245.305,
        245.805,
        246.39,
        246.13,
        245.82,
        245.97
      ]
    },
    "VIXY": {
      "ticker": "VIXY",
      "currentPrice": 36.25,
      "change": 0.759999999999998,
      "changePercent": 2.1414482952944436,
      "previousClose": 35.49,
      "high": 37.28,
      "low": 35.93,
      "open": 36.08,
      "sparkline": [
        37.1,
        36.81,
        37.02,
        37.2,
        36.91,
        37.07,
        37.06,
        36.56,
        36.72,
        36.66,
        36.51,
        36.49,
        36.56,
        36.7,
        36.47,
        36.26,
        35.98,
        36.14,
        36.25,
        36.27
      ]
    },
    "IEF": {
      "ticker": "IEF",
      "currentPrice": 94.76,
      "change": 0.1700000000000017,
      "changePercent": 0.17972301511787894,
      "previousClose": 94.59,
      "high": 94.78,
      "low": 94.355,
      "open": 94.44,
      "sparkline": [
        94.495,
        94.53,
        94.5,
        94.49,
        94.55,
        94.52,
        94.54,
        94.56,
        94.62,
        94.63,
        94.66,
        94.63,
        94.65,
        94.64,
        94.71,
        94.73,
        94.76,
        94.75,
        94.74,
        94.74
      ]
    },
    "URTH": {
      "ticker": "URTH",
      "currentPrice": 177.07,
      "change": -0.9699999999999989,
      "changePercent": -0.5448213884520327,
      "previousClose": 178.04,
      "high": 177.33,
      "low": 176.28,
      "open": 177.16500000000002
    },
    "ACWI": {
      "ticker": "ACWI",
      "currentPrice": 135.84,
      "change": -0.539999999999992,
      "changePercent": -0.39595248570170993,
      "previousClose": 136.38,
      "high": 136.12,
      "low": 135.18,
      "open": 135.945
    },
    "RSP": {
      "ticker": "RSP",
      "currentPrice": 190.41,
      "change": -0.6700000000000159,
      "changePercent": -0.3506384760309901,
      "previousClose": 191.08,
      "high": 190.96,
      "low": 189.12,
      "open": 190.96
    },
    "VTV": {
      "ticker": "VTV",
      "currentPrice": 195.26,
      "change": -1.0100000000000193,
      "changePercent": -0.5145972384979973,
      "previousClose": 196.27,
      "high": 195.46,
      "low": 194.115,
      "open": 195.01
    },
    "VUG": {
      "ticker": "VUG",
      "currentPrice": 426.79,
      "change": -5.930000000000007,
      "changePercent": -1.3704011832131646,
      "previousClose": 432.72,
      "high": 432.38,
      "low": 425.395,
      "open": 432.38
    },
    "XLK": {
      "ticker": "XLK",
      "currentPrice": 131.37,
      "change": -1.1299999999999955,
      "changePercent": -0.852830188679242,
      "previousClose": 132.5,
      "high": 132.3,
      "low": 130.35,
      "open": 132.3
    },
    "XLF": {
      "ticker": "XLF",
      "currentPrice": 48.43,
      "change": -0.6199999999999974,
      "changePercent": -1.2640163098878645,
      "previousClose": 49.05,
      "high": 48.995000000000005,
      "low": 47.95,
      "open": 48.995000000000005
    },
    "XLE": {
      "ticker": "XLE",
      "currentPrice": 62.69,
      "change": 1.1699999999999946,
      "changePercent": 1.9018205461638404,
      "previousClose": 61.52,
      "high": 62.715,
      "low": 61.26,
      "open": 61.665
    },
    "XLV": {
      "ticker": "XLV",
      "currentPrice": 144.81,
      "change": -0.9300000000000068,
      "changePercent": -0.638122684232199,
      "previousClose": 145.74,
      "high": 145.8,
      "low": 144.29,
      "open": 145.78
    },
    "XLY": {
      "ticker": "XLY",
      "currentPrice": 106.99,
      "change": -1.8400000000000034,
      "changePercent": -1.6907102820913382,
      "previousClose": 108.83,
      "high": 108.84,
      "low": 106.49,
      "open": 108.84
    },
    "XLP": {
      "ticker": "XLP",
      "currentPrice": 82.24,
      "change": 1.0999999999999943,
      "changePercent": 1.3556815380823197,
      "previousClose": 81.14,
      "high": 82.255,
      "low": 80.99,
      "open": 81.22999999999999
    },
    "AAPL": {
      "ticker": "AAPL",
      "currentPrice": 252.49,
      "change": -0.39999999999997726,
      "changePercent": -0.15817153703190215,
      "previousClose": 252.89,
      "high": 255.493,
      "low": 251.8,
      "open": 254.005
    },
    "MSFT": {
      "ticker": "MSFT",
      "currentPrice": 359.69,
      "change": -6.28000000000003,
      "changePercent": -1.7159876492608763,
      "previousClose": 365.97,
      "high": 364.65,
      "low": 356.58,
      "open": 364.65
    },
    "NVDA": {
      "ticker": "NVDA",
      "currentPrice": 169.47,
      "change": -1.7700000000000102,
      "changePercent": -1.0336370007007767,
      "previousClose": 171.24,
      "high": 171.35500000000002,
      "low": 167.55,
      "open": 171.35500000000002
    },
    "AMZN": {
      "ticker": "AMZN",
      "currentPrice": 201.05,
      "change": -6.489999999999981,
      "changePercent": -3.1271080273682093,
      "previousClose": 207.54,
      "high": 207.47250000000003,
      "low": 200.27,
      "open": 207.47250000000003
    },
    "JPM": {
      "ticker": "JPM",
      "currentPrice": 286.47,
      "change": -5.189999999999998,
      "changePercent": -1.7794692450113134,
      "previousClose": 291.66,
      "high": 290.435,
      "low": 284.5,
      "open": 290.435
    }
  },
  "compassData": {
    "direction": {
      "spy": {
        "price": 640.95,
        "ma200": 661.67,
        "percentVs200MA": -3.13,
        "dailyChange": -0.64
      },
      "qqq": {
        "price": 568.465,
        "ma200": 594.1,
        "percentVs200MA": -4.31,
        "dailyChange": -0.93
      },
      "iwm": {
        "price": 246.015,
        "ma200": 242.14,
        "percentVs200MA": 1.6,
        "dailyChange": -0.58
      }
    },
    "volatility": {
      "vix": {
        "value": 28.81,
        "dailyChange": 1.37,
        "isContango": false
      },
      "putCall": {
        "ratio": 0.85,
        "change": 0
      }
    },
    "breadth": {
      "advancers": 1800,
      "decliners": 1200,
      "percentAbove200MA": 50,
      "percentAbove200MAChange": 0,
      "newHighs": 75,
      "newLows": 30
    },
    "credit": {
      "treasury10Y": 4.15,
      "treasury2Y": 3.95,
      "yieldCurveSpread": 0.2,
      "yieldCurveChange": 0,
      "hySpread": 3.5,
      "hySpreadChange": 0,
      "igSpread": 1.2,
      "igSpreadChange": 0
    },
    "sentiment": {
      "fearGreed": 50,
      "fearGreedChange": 0,
      "bulls": 35.2,
      "bears": 29.8,
      "bullsChange": 1.2,
      "bearsChange": -0.8
    },
    "global": {
      "acwi": {
        "price": 135.81,
        "percentVs50MA": -5.68,
        "dailyChange": -0.42
      },
      "vstoxx": {
        "value": 17,
        "change": 0
      },
      "pmi": {
        "value": 52.3,
        "change": 0.4
      }
    }
  }
}