{
  "lastUpdated": "2026-03-09T18:01:43.164Z",
  "marketOpen": true,
  "instruments": {
    "SPY": {
      "ticker": "SPY",
      "currentPrice": 669.15,
      "change": -3.230000000000018,
      "changePercent": -0.4803831166899697,
      "previousClose": 672.38,
      "high": 672.25,
      "low": 662.39,
      "open": 663.31,
      "sparkline": [
        670.87,
        670.81,
        671.02,
        671.82,
        671.96,
        671.57,
        671.25,
        670.78,
        670.76,
        670.71,
        669.77,
        669.04,
        668.9,
        668.83,
        668.47,
        668.24,
        668.65,
        669.19,
        668.79,
        669.09
      ]
    },
    "QQQ": {
      "ticker": "QQQ",
      "currentPrice": 598.85,
      "change": -0.8999999999999773,
      "changePercent": -0.15006252605251807,
      "previousClose": 599.75,
      "high": 601.85,
      "low": 590.64,
      "open": 590.64,
      "sparkline": [
        600.42,
        600.52,
        600.92,
        601.58,
        601.54,
        601.1,
        600.895,
        600.37,
        600.32,
        600.32,
        599.3,
        598.7,
        598.56,
        598.39,
        598.17,
        597.88,
        598.18,
        598.85,
        598.53,
        598.71
      ]
    },
    "IWM": {
      "ticker": "IWM",
      "currentPrice": 248.06,
      "change": -2.829999999999984,
      "changePercent": -1.1279843756227765,
      "previousClose": 250.89,
      "high": 249.89,
      "low": 244.24,
      "open": 244.24,
      "sparkline": [
        248.93,
        248.91,
        249.04,
        249.52,
        249.665,
        249.605,
        249.455,
        249.205,
        249.06,
        248.99,
        248.43,
        248.28,
        248.2,
        248.24,
        248,
        247.78,
        247.87,
        248.105,
        247.97,
        248.035
      ]
    },
    "VIXY": {
      "ticker": "VIXY",
      "currentPrice": 33.4,
      "change": -1.0500000000000043,
      "changePercent": -3.047895500725702,
      "previousClose": 34.45,
      "high": 36.195,
      "low": 32.425,
      "open": 34.919999999999995,
      "sparkline": [
        33,
        32.86,
        32.8,
        32.62,
        32.47,
        32.64,
        32.6,
        32.74,
        32.8,
        32.95,
        33.25,
        33.51,
        33.44,
        33.49,
        33.605,
        33.67,
        33.54,
        33.4,
        33.505,
        33.39
      ]
    },
    "IEF": {
      "ticker": "IEF",
      "currentPrice": 96.56,
      "change": 0.10999999999999943,
      "changePercent": 0.11404872991187084,
      "previousClose": 96.45,
      "high": 96.635,
      "low": 96.25,
      "open": 96.31,
      "sparkline": [
        96.555,
        96.54,
        96.59,
        96.61,
        96.63,
        96.61,
        96.57,
        96.55,
        96.55,
        96.56,
        96.56,
        96.57,
        96.575,
        96.58,
        96.555,
        96.545,
        96.53,
        96.54,
        96.54,
        96.54
      ]
    },
    "URTH": {
      "ticker": "URTH",
      "currentPrice": 183.7,
      "change": -1.2800000000000011,
      "changePercent": -0.6919666991026063,
      "previousClose": 184.98,
      "high": 184.63,
      "low": 181.76,
      "open": 182.96
    },
    "ACWI": {
      "ticker": "ACWI",
      "currentPrice": 140.92,
      "change": -0.7600000000000193,
      "changePercent": -0.5364201016375065,
      "previousClose": 141.68,
      "high": 141.64,
      "low": 139.25,
      "open": 140.33
    },
    "RSP": {
      "ticker": "RSP",
      "currentPrice": 195.98,
      "change": -2.170000000000016,
      "changePercent": -1.095129952056531,
      "previousClose": 198.15,
      "high": 196.91,
      "low": 193.97,
      "open": 196.24
    },
    "VTV": {
      "ticker": "VTV",
      "currentPrice": 198.05,
      "change": -1.9799999999999898,
      "changePercent": -0.9898515222716542,
      "previousClose": 200.03,
      "high": 198.935,
      "low": 196.42,
      "open": 196.96
    },
    "VUG": {
      "ticker": "VUG",
      "currentPrice": 457.42,
      "change": -0.6599999999999682,
      "changePercent": -0.14407963674466648,
      "previousClose": 458.08,
      "high": 459.74,
      "low": 452.05,
      "open": 454.19
    },
    "XLK": {
      "ticker": "XLK",
      "currentPrice": 137.48,
      "change": 0.18999999999999773,
      "changePercent": 0.1383931823148064,
      "previousClose": 137.29,
      "high": 138.42,
      "low": 135.1,
      "open": 135.1
    },
    "XLF": {
      "ticker": "XLF",
      "currentPrice": 49.58,
      "change": -0.990000000000002,
      "changePercent": -1.9576824204073602,
      "previousClose": 50.57,
      "high": 50.085,
      "low": 49.18,
      "open": 49.65
    },
    "XLE": {
      "ticker": "XLE",
      "currentPrice": 56.49,
      "change": -0.0799999999999983,
      "changePercent": -0.1414177125684962,
      "previousClose": 56.57,
      "high": 57.64,
      "low": 56.27,
      "open": 57.64
    },
    "XLV": {
      "ticker": "XLV",
      "currentPrice": 152.33,
      "change": -0.3699999999999761,
      "changePercent": -0.24230517354287892,
      "previousClose": 152.7,
      "high": 153.28,
      "low": 151,
      "open": 151
    },
    "XLY": {
      "ticker": "XLY",
      "currentPrice": 112.47,
      "change": -1.9699999999999989,
      "changePercent": -1.7214260747990202,
      "previousClose": 114.44,
      "high": 113.12,
      "low": 110.99,
      "open": 112.57
    },
    "XLP": {
      "ticker": "XLP",
      "currentPrice": 85.39,
      "change": -0.39000000000000057,
      "changePercent": -0.45465143390067675,
      "previousClose": 85.78,
      "high": 85.7,
      "low": 84.8,
      "open": 85.4
    },
    "AAPL": {
      "ticker": "AAPL",
      "currentPrice": 256.38,
      "change": -1.079999999999984,
      "changePercent": -0.41948263807969555,
      "previousClose": 257.46,
      "high": 258.27,
      "low": 253.5,
      "open": 253.5
    },
    "MSFT": {
      "ticker": "MSFT",
      "currentPrice": 405.29,
      "change": -3.669999999999959,
      "changePercent": -0.8973982785602405,
      "previousClose": 408.96,
      "high": 409.17,
      "low": 402.95,
      "open": 402.95
    },
    "NVDA": {
      "ticker": "NVDA",
      "currentPrice": 179.91,
      "change": 2.0900000000000034,
      "changePercent": 1.175345855359354,
      "previousClose": 177.82,
      "high": 180.91,
      "low": 175.56,
      "open": 175.72
    },
    "AMZN": {
      "ticker": "AMZN",
      "currentPrice": 209.49,
      "change": -3.719999999999999,
      "changePercent": -1.744758688616856,
      "previousClose": 213.21,
      "high": 212.295,
      "low": 207.11,
      "open": 208.81
    },
    "JPM": {
      "ticker": "JPM",
      "currentPrice": 285.6,
      "change": -3.8799999999999955,
      "changePercent": -1.3403343927041576,
      "previousClose": 289.48,
      "high": 287.2,
      "low": 280.45,
      "open": 283.76
    }
  },
  "compassData": {
    "direction": {
      "spy": {
        "price": 669.216,
        "ma200": 656.82,
        "percentVs200MA": 1.89,
        "dailyChange": -0.47
      },
      "qqq": {
        "price": 598.96,
        "ma200": 589.21,
        "percentVs200MA": 1.65,
        "dailyChange": -0.13
      },
      "iwm": {
        "price": 248.16,
        "ma200": 239.26,
        "percentVs200MA": 3.72,
        "dailyChange": -1.09
      }
    },
    "volatility": {
      "vix": {
        "value": 27.97,
        "dailyChange": -1.52,
        "isContango": false
      },
      "putCall": {
        "ratio": 0.85,
        "change": 0
      }
    },
    "breadth": {
      "advancers": 1800,
      "decliners": 1200,
      "percentAbove200MA": 80,
      "percentAbove200MAChange": 0,
      "newHighs": 75,
      "newLows": 30
    },
    "credit": {
      "treasury10Y": 4.15,
      "treasury2Y": 3.95,
      "yieldCurveSpread": 0.2,
      "yieldCurveChange": 0,
      "hySpread": 3.5,
      "hySpreadChange": 0,
      "igSpread": 1.2,
      "igSpreadChange": 0
    },
    "sentiment": {
      "fearGreed": 50,
      "fearGreedChange": 0,
      "bulls": 35.2,
      "bears": 29.8,
      "bullsChange": 1.2,
      "bearsChange": -0.8
    },
    "global": {
      "acwi": {
        "price": 140.95,
        "percentVs50MA": -2.84,
        "dailyChange": -0.52
      },
      "vstoxx": {
        "value": 17,
        "change": 0
      },
      "pmi": {
        "value": 52.3,
        "change": 0.4
      }
    }
  }
}